dhubbard_sphinx_markdown_tables-0.1.140866.dist-info/LICENSE.txt
dhubbard_sphinx_markdown_tables-0.1.140866.dist-info/METADATA
dhubbard_sphinx_markdown_tables-0.1.140866.dist-info/RECORD
dhubbard_sphinx_markdown_tables-0.1.140866.dist-info/WHEEL
dhubbard_sphinx_markdown_tables-0.1.140866.dist-info/top_level.txt
dhubbard_sphinx_markdown_tables-0.1.140866.dist-info/zip-safe
sphinx_markdown_tables/__init__.py
