Metadata-Version: 2.1
Name: dhubbard-sphinx-markdown-tables
Version: 0.1.140866
Summary: A Sphinx extension for rendering tables written in markdown
Home-page: https://github.com/dwighthubbard/sphinx-markdown-tables
Author: Dwight Hubbard
Author-email: 254983+dwighthubbard@users.noreply.github.com
License: GPLv3
Project-URL: Bug Reports, https://github.com/dwighthubbard/sphinx-markdown-tables/issues
Project-URL: Source, https://github.com/dwighthubbard/sphinx-markdown-tables
Keywords: sphinx markdown tables
Platform: UNKNOWN
Classifier: Development Status :: 4 - Beta
Classifier: Intended Audience :: Developers
Classifier: License :: OSI Approved :: GNU General Public License v3 (GPLv3)
Classifier: Programming Language :: Python :: 3 :: Only
Classifier: Programming Language :: Python :: 3.6
Classifier: Programming Language :: Python :: 3.7
Classifier: Programming Language :: Python :: 3.8
Requires-Python: >="3.6"
Provides-Extra: test
Requires-Dist: markdown (>=2.6.11)
Requires-Dist: recommonmark
Requires-Dist: setuptools (>38.0.0)
Provides-Extra: test
Requires-Dist: pytest; extra == 'test'
Requires-Dist: pytest-cov; extra == 'test'
Requires-Dist: sphinx-testing; extra == 'test'
